socialvec/.DS_Store
socialvec/__init__.py
socialvec/cli.py
socialvec/config.yaml
socialvec/socialvec.py
socialvec/models/SocialVec_age_2022.h5
socialvec/models/SocialVec_children_2022.h5
socialvec/models/SocialVec_education_2022.h5
socialvec/models/SocialVec_ethnicity_2022.h5
socialvec/models/SocialVec_gender_2022.h5
socialvec/models/SocialVec_income_2022.h5
socialvec/models/SocialVec_political_2022.h5
socialvec-0.1.7.1.dist-info/AUTHORS.rst
socialvec-0.1.7.1.dist-info/LICENSE
socialvec-0.1.7.1.dist-info/METADATA
socialvec-0.1.7.1.dist-info/WHEEL
socialvec-0.1.7.1.dist-info/entry_points.txt
socialvec-0.1.7.1.dist-info/top_level.txt
socialvec-0.1.7.1.dist-info/RECORD
